tests/__init__.py
tests/test_base_tools.py
tests/test_dir_tools.py
tests/test_file_operations.py
tests/test_git_tools.py
tests/test_server.py
tests/test_xml_parser.py
orange_mcp_server_code_assist-0.2.0.dist-info/METADATA
orange_mcp_server_code_assist-0.2.0.dist-info/WHEEL
orange_mcp_server_code_assist-0.2.0.dist-info/entry_points.txt
orange_mcp_server_code_assist-0.2.0.dist-info/RECORD
