Metadata-Version: 2.4
Name: orange-mcp-server-code-assist
Version: 0.2.0
Summary: MCP Code Assist Server
Requires-Python: >=3.11
Requires-Dist: aiofiles>=24.0.0
Requires-Dist: click>=8.1.7
Requires-Dist: gitpython>=3.1.40
Requires-Dist: mcp>=1.2.0
Requires-Dist: pydantic>=2.0.0
Requires-Dist: xmlschema>=3.4.3
Provides-Extra: dev
Requires-Dist: pre-commit>=4.0.1; extra == 'dev'
Requires-Dist: pytest-asyncio>=0.25.0; extra == 'dev'
Requires-Dist: pytest>=8.0.0; extra == 'dev'
Requires-Dist: ruff>=0.9.2; extra == 'dev'
